{
	"pageSize": 20,
	"pageIndex": 1,
	"total": 1000,
	"table": [
		{
			"sysModule": "采购",
			"processRank": 2,
			"auditor": ["陈小美", "王大帅"],
			"remarkWay": ["站内信息","手机信息","邮件信息"]
		},
		{
			"sysModule": "销售",
			"processRank": 1,
			"auditor": ["陈小美", "王大帅"],
			"remarkWay": ["站内信息","手机信息","邮件信息"]
		},
		{
			"sysModule": "仓库",
			"processRank": 1,
			"auditor": ["陈小美", "王大帅"],
			"remarkWay": ["站内信息","手机信息","邮件信息"]
		}
	],
	"sysModuleOptions": [
		{
			"label": "采购",
			"value": "选项1"
		},
		{
			"label": "销售",
			"value": "选项2"
		},
		{
			"label": "仓库",
			"value": "选项3"
		}
	],
	"processLevelOptions": [
		{
			"label": "一级审核",
			"value": 1
		},
		{
			"label": "二级审核",
			"value": 2
		}
	],
	"auditors": [
		{
			"name": "王某",
			"value": 1
		},
		{
			"name": "李某",
			"value": 2
		},
		{
			"name": "张某",
			"value": 3
		},
		{
			"name": "赵某",
			"value": 4
		}
	],
	"bosses": [
		{
			"name": "钱总",
			"value": 1001
		},
		{
			"name": "孙总",
			"value": 1002
		}
	]
}