[{
		"id": "nav_002",
		"name": "系统设置",
		"number": "a1sd2a3s",
		"address": "/address/xxx",
		"target": "iframe",
		"menu": true,
		"unfold": false,
		"public": false,
		"valid": true,
		"describe": "一些描述....",
		"hideColumn": "测试",
		"children": [{
				"id": "systemParameter",
				"name": "系统参数",
				"number": "a1sd2a3s",
				"address": "/address/xxx",
				"target": "iframe",
				"menu": true,
				"unfold": false,
				"public": false,
				"valid": true,
				"describe": "一些描述....",
				"hideColumn": "测试"
			},
			{
				"id": "phoneInfo",
				"name": "手机信息",
				"number": "a1sd2a3s",
				"address": "/address/xxx",
				"target": "iframe",
				"menu": true,
				"unfold": false,
				"public": false,
				"valid": true,
				"describe": "一些描述....",
				"hideColumn": "测试"
			}
		]
	},
	{
		"id": "nav_003",
		"name": "基础资料",
		"number": "a1sd2a3s",
		"address": "/address/xxx",
		"target": "iframe",
		"menu": true,
		"unfold": false,
		"public": false,
		"valid": true,
		"describe": "一些描述....",
		"hideColumn": "测试",
		"children": [{
				"id": "menuManagement",
				"name": "功能菜单管理",
				"number": "a1sd2a3s",
				"address": "/address/xxx",
				"target": "iframe",
				"menu": true,
				"unfold": false,
				"public": false,
				"valid": true,
				"describe": "一些描述....",
				"hideColumn": "测试"
			},
			{
				"id": "dataDictionary",
				"name": "数据字典",
				"number": "a1sd2a3s",
				"address": "/address/xxx",
				"target": "iframe",
				"menu": true,
				"unfold": false,
				"public": false,
				"valid": true,
				"describe": "一些描述....",
				"hideColumn": "测试"
			}
		]
	}
]